train_toolkits/__init__.py
train_toolkits/docs/MicrosoftYaHei-01.ttf
train_toolkits/docs/__init__.py
train_toolkits/docs/draw/__init__.py
train_toolkits/docs/draw/show.ipynb
train_toolkits/docs/with_resnet/__init__.py
train_toolkits/docs/with_resnet/resnet101.ipynb
train_toolkits/docs/with_resnet/resnet101_handwrite.ipynb
train_toolkits/docs/with_rnn/__init__.py
train_toolkits/docs/with_rnn/faiss.ipynb
train_toolkits/docs/with_rnn/lstm.ipynb
train_toolkits/docs/with_rnn/rnn.ipynb
train_toolkits/docs/with_sklearn/__init__.py
train_toolkits/docs/with_sklearn/句子分类-影评.ipynb
train_toolkits/docs/with_sklearn/图像分类-mnist.ipynb
train_toolkits/docs/with_sklearn/图像分类-猫狗.ipynb
train_toolkits/docs/with_sklearn/数据分类-iris.ipynb
train_toolkits/docs/文本分析处理/__init__.py
train_toolkits/docs/文本分析处理/test-01.ipynb
train_toolkits/docs/文本分析处理/test_02.ipynb
train_toolkits/docs/文本分析处理/text-data-analysis-01_text-preprocessing.ipynb
train_toolkits/docs/文本分析处理/text-data-analysis-02_N-gram-LMs.ipynb
train_toolkits/docs/文本分析处理/text-data-analysis-03_word-embeddings.ipynb
train_toolkits/docs/文本分析处理/text-data-analysis-04_Pytorch-introduction.ipynb
train_toolkits/docs/文本分析处理/text-data-analysis-05_RNN-classification.ipynb
train_toolkits/docs/文本分析处理/text-data-analysis-06_Transformer-LMs.ipynb
train_toolkits/docs/爬虫/Lab2-1 - Gazpacho爬虫.ipynb
train_toolkits/docs/爬虫/Lab2-2 - 爬虫 - 豆瓣读书TOP250书评爬取分析 - 词云 - 地图.ipynb
train_toolkits/docs/爬虫/__init__.py
train_toolkits/docs/竞争分析/1_市场分析.ipynb
train_toolkits/docs/竞争分析/2_细分市场的趋势.ipynb
train_toolkits/docs/竞争分析/3_竞争分析.ipynb
train_toolkits/docs/竞争分析/__init__.py
train_toolkits/docs/竞争分析/代理.ipynb
train_toolkits/docs/竞争分析/简单回归.ipynb
train_toolkits/docs/竞争分析/说明.ipynb
train_toolkits/docs/考试解答/__init__.py
train_toolkits/docs/考试解答/msyh.ttc
train_toolkits/docs/考试解答/试题1 参考答案.ipynb
train_toolkits/docs/考试解答/试题1 图书信息数据分析 - 三维散点图分析 (1).ipynb
train_toolkits/docs/考试解答/试题1 图书信息数据分析 - 三维散点图分析.ipynb
train_toolkits/docs/考试解答/试题2  图书评论词云进阶分析.ipynb
train_toolkits/docs/考试解答/试题2 参考答案.ipynb
train_toolkits-0.0.3.dist-info/METADATA
train_toolkits-0.0.3.dist-info/WHEEL
train_toolkits-0.0.3.dist-info/top_level.txt
train_toolkits-0.0.3.dist-info/RECORD
