Metadata-Version: 2.1
Name: train_toolkits
Version: 0.0.3
Summary: train_toolkits
Home-page: https://github.com/hky3535/train_toolkits
Author: hky3535
Author-email: hky3535@163.com
Classifier: Programming Language :: Python :: 3
Classifier: License :: OSI Approved :: MIT License
Classifier: Operating System :: OS Independent
Requires-Python: >=3.6
